sudoku_solver_ocr/__init__.py
sudoku_solver_ocr/__main__.py
sudoku_solver_ocr/main.py
sudoku_solver_ocr/sudoku_ocr.py
sudoku_solver_ocr/sudoku_solver.py
sudoku_solver_ocr/sudoku_utils.py
sudoku_solver_ocr-0.4.dist-info/METADATA
sudoku_solver_ocr-0.4.dist-info/WHEEL
sudoku_solver_ocr-0.4.dist-info/top_level.txt
sudoku_solver_ocr-0.4.dist-info/RECORD
