Metadata-Version: 2.4
Name: sudoku_solver_ocr
Version: 0.4
Summary: This program first converts a screenshot of a sudoku grid into plain text. Afterwards, it will solve the sudoku puzzle, display the result and save the solution as a .csv file.
Home-page: https://github.com/COSC111-sudoku-solver/sudoku-solver
Author: k1m-ch1
Requires-Dist: opencv-python
Requires-Dist: pytesseract
Dynamic: author
Dynamic: description
Dynamic: description-content-type
Dynamic: home-page
Dynamic: requires-dist
Dynamic: summary
